uplaybook/__init__.py
uplaybook/cli.py
uplaybook/core.py
uplaybook/fernetreader.py
uplaybook/fs.py
uplaybook/internals.py
uplaybook/pyinfra/__init__.py
uplaybook/pyinfra/apk.py
uplaybook/pyinfra/apt.py
uplaybook/pyinfra/brew.py
uplaybook/pyinfra/bsdinit.py
uplaybook/pyinfra/choco.py
uplaybook/pyinfra/dnf.py
uplaybook/pyinfra/files.py
uplaybook/pyinfra/gem.py
uplaybook/pyinfra/git.py
uplaybook/pyinfra/iptables.py
uplaybook/pyinfra/launchd.py
uplaybook/pyinfra/lxd.py
uplaybook/pyinfra/mysql.py
uplaybook/pyinfra/npm.py
uplaybook/pyinfra/openrc.py
uplaybook/pyinfra/pacman.py
uplaybook/pyinfra/pip.py
uplaybook/pyinfra/pkg.py
uplaybook/pyinfra/pkgin.py
uplaybook/pyinfra/postgresql.py
uplaybook/pyinfra/puppet.py
uplaybook/pyinfra/pyinfra_stubs
uplaybook/pyinfra/server.py
uplaybook/pyinfra/ssh.py
uplaybook/pyinfra/systemd.py
uplaybook/pyinfra/sysvinit.py
uplaybook/pyinfra/upstart.py
uplaybook/pyinfra/vzctl.py
uplaybook/pyinfra/windows.py
uplaybook/pyinfra/windows_files.py
uplaybook/pyinfra/xbps.py
uplaybook/pyinfra/yum.py
uplaybook/pyinfra/zypper.py
uplaybook-0.9.7.dist-info/LICENSE
uplaybook-0.9.7.dist-info/METADATA
uplaybook-0.9.7.dist-info/WHEEL
uplaybook-0.9.7.dist-info/entry_points.txt
uplaybook-0.9.7.dist-info/RECORD
