Metadata-Version: 2.1
Name: uplaybook
Version: 0.9.7
Summary: A python-syntax declarative IT automation tool.
License: CC0-1.0
Author: Sean Reifschneider
Author-email: jafo00@gmail.com
Requires-Python: >=3.10,<4.0
Classifier: License :: CC0 1.0 Universal (CC0 1.0) Public Domain Dedication
Classifier: Programming Language :: Python :: 3
Classifier: Programming Language :: Python :: 3.10
Classifier: Programming Language :: Python :: 3.11
Classifier: Programming Language :: Python :: 3.12
Requires-Dist: jinja2 (>=3.1.2,<4.0.0)
Requires-Dist: pyinfra
Requires-Dist: rich
Requires-Dist: symbolicmode (>=2.0.0,<3.0.0)
